[{"ticker":"005930","name":"삼성전자","close":270000.0,"change_pct":3.6468,"stage":{"stage":2,"label":"2단계 · 상승 추세","desc":"기관 매집이 유효한 매수 가능 국면 · 50일선 하회 — 2단계 내 눌림/약화 주의","confidence":0.8},"template":{"conds":{"T1":true,"T2":true,"T3":true,"T4":true,"T5":false,"T6":true,"T7":false,"T8":true},"passed":6,"total":8,"values":{"close":270000.0,"ma50":305180.0,"ma150":218752.0,"ma200":188689.0,"ma200_slope1m":22963.5,"pct_above_lo52":341.18,"pct_from_hi52":-27.9,"rs":94.9},"rs":94.9},"vcp":{"valid":false,"status":"NONE","pivot":284500.0,"pivot_date":"2026-07-15","depths":[17.2,22.3,15.8,10.8,17.1,15.6],"footprint":"17%-22%-16%-11%-17%-16% 6T","base_days":23,"vdu":0.71,"vol_ratio":0.51,"dist_to_pivot_pct":-5.1,"notes":["✓ 수축 횟수 6회","✓ 베이스 깊이 17%","✗ 수축 축소 위반 2회","✗ 최종 수축 15.6%","✓ 베이스 23일","✓ 드라이업 0.71 (기준 ≤0.85)"],"contractions":[["2026-06-19",374500.0,"2026-06-23",310000.0],["2026-06-25",362500.0,"2026-07-02",281500.0],["2026-07-06",325000.0,"2026-07-08",273500.0],["2026-07-08",300000.0,"2026-07-09",267500.0],["2026-07-10",298000.0,"2026-07-14",247000.0],["2026-07-15",284500.0,"2026-07-20",240000.0]]}},{"ticker":"196170","name":"알테오젠","close":306500.0,"change_pct":14.3657,"stage":{"stage":4,"label":"4단계 · 하락 추세","desc":"매도/관망 국면 — 신규 매수 금지","confidence":1.0},"template":{"conds":{"T1":false,"T2":false,"T3":false,"T4":false,"T5":false,"T6":false,"T7":false,"T8":false},"passed":0,"total":8,"values":{"close":306500.0,"ma50":340000.0,"ma150":377960.0,"ma200":406985.0,"ma200_slope1m":-15407.5,"pct_above_lo52":21.15,"pct_from_hi52":-46.13,"rs":33.9},"rs":33.9},"vcp":{"valid":false,"status":"NONE","pivot":295500.0,"pivot_date":"2026-07-15","depths":[14.0,22.6,26.5,12.9],"footprint":"14%-23%-26%-13% 4T","base_days":19,"vdu":0.67,"vol_ratio":0.99,"dist_to_pivot_pct":3.72,"notes":["✓ 수축 횟수 4회","✓ 베이스 깊이 14%","✗ 수축 축소 위반 2회","✗ 최종 수축 12.9%","✗ 베이스 19일","✓ 드라이업 0.67 (기준 ≤0.85)"],"contractions":[["2026-06-25",397500.0,"2026-06-26",342000.0],["2026-06-29",385500.0,"2026-07-10",298500.0],["2026-07-13",344000.0,"2026-07-14",253000.0],["2026-07-15",295500.0,"2026-07-21",257500.0]]}},{"ticker":"950160","name":"코오롱티슈진","close":21050.0,"change_pct":-29.9501,"stage":{"stage":3,"label":"3단계 · 천장 형성","desc":"분산 신호 — 신규 매수 금지, 보유분 관리","confidence":0.87},"template":{"conds":{"T1":false,"T2":true,"T3":true,"T4":true,"T5":false,"T6":false,"T7":false,"T8":false},"passed":3,"total":8,"values":{"close":21050.0,"ma50":94404.0,"ma150":94266.67,"ma200":84417.5,"ma200_slope1m":3746.75,"pct_above_lo52":0.0,"pct_from_hi52":-85.87,"rs":1.1},"rs":1.1},"vcp":{"valid":false,"status":"NONE","pivot":65100.0,"pivot_date":"2026-07-20","depths":[19.8,14.2,18.0,32.1,31.7,67.7],"footprint":"20%-14%-18%-32%-32%-68% 6T","base_days":17,"vdu":1.08,"vol_ratio":0.75,"dist_to_pivot_pct":-67.67,"notes":["✓ 수축 횟수 6회","✓ 베이스 깊이 20%","✗ 수축 축소 위반 3회","✗ 최종 수축 67.7%","✗ 베이스 17일","△ 드라이업 1.08 (기준 ≤0.85)"],"contractions":[["2026-06-29",102300.0,"2026-07-03",82000.0],["2026-07-06",96800.0,"2026-07-06",83100.0],["2026-07-07",96300.0,"2026-07-10",79000.0],["2026-07-13",92800.0,"2026-07-14",63000.0],["2026-07-16",81100.0,"2026-07-16",55400.0],["2026-07-20",65100.0,"2026-07-23",21050.0]]}},{"ticker":"000660","name":"SK하이닉스","close":1919000.0,"change_pct":4.8634,"stage":{"stage":2,"label":"2단계 · 상승 추세","desc":"기관 매집이 유효한 매수 가능 국면 · 50일선 하회 — 2단계 내 눌림/약화 주의","confidence":0.8},"template":{"conds":{"T1":true,"T2":true,"T3":true,"T4":true,"T5":false,"T6":true,"T7":false,"T8":true},"passed":6,"total":8,"values":{"close":1919000.0,"ma50":2200120.0,"ma150":1346620.0,"ma200":1137910.0,"ma200_slope1m":201680.0,"pct_above_lo52":683.27,"pct_from_hi52":-35.75,"rs":97.4},"rs":97.4},"vcp":{"valid":false,"status":"NONE","pivot":2171000.0,"pivot_date":"2026-07-15","depths":[26.8,16.7,16.9,10.2,27.2,20.2],"footprint":"27%-17%-17%-10%-27%-20% 6T","base_days":19,"vdu":0.85,"vol_ratio":0.69,"dist_to_pivot_pct":-11.61,"notes":["✓ 수축 횟수 6회","✓ 베이스 깊이 27%","✓ 수축 축소 위반 1회","✗ 최종 수축 20.2%","✗ 베이스 19일","✓ 드라이업 0.85 (기준 ≤0.85)"],"contractions":[["2026-06-25",2987000.0,"2026-07-02",2187000.0],["2026-07-03",2454000.0,"2026-07-03",2045000.0],["2026-07-06",2497000.0,"2026-07-08",2076000.0],["2026-07-08",2329000.0,"2026-07-09",2091000.0],["2026-07-10",2305000.0,"2026-07-14",1678000.0],["2026-07-15",2171000.0,"2026-07-21",1732000.0]]}},{"ticker":"475960","name":"토모큐브","close":35850.0,"change_pct":2.4286,"stage":{"stage":3,"label":"3단계 · 천장 형성","desc":"분산 신호 — 신규 매수 금지, 보유분 관리","confidence":0.62},"template":{"conds":{"T1":false,"T2":true,"T3":false,"T4":false,"T5":false,"T6":true,"T7":false,"T8":false},"passed":2,"total":8,"values":{"close":35850.0,"ma50":39163.0,"ma150":48769.33,"ma200":47856.25,"ma200_slope1m":-1072.75,"pct_above_lo52":59.33,"pct_from_hi52":-47.12,"rs":52.9},"rs":52.9},"vcp":{"valid":false,"status":"NONE","pivot":39400.0,"pivot_date":"2026-07-15","depths":[12.2],"footprint":"12% 1T","base_days":5,"vdu":0.71,"vol_ratio":0.36,"dist_to_pivot_pct":-9.01,"notes":["✗ 수축 횟수 1회","✓ 베이스 깊이 12%","✓ 수축 축소 위반 0회","✗ 최종 수축 12.2%","✗ 베이스 5일","✓ 드라이업 0.71 (기준 ≤0.85)"],"contractions":[["2026-07-15",39400.0,"2026-07-21",34600.0]]}},{"ticker":"347850","name":"디앤디파마텍","close":64000.0,"change_pct":8.4746,"stage":{"stage":4,"label":"4단계 · 하락 추세","desc":"매도/관망 국면 — 신규 매수 금지","confidence":1.0},"template":{"conds":{"T1":false,"T2":false,"T3":false,"T4":false,"T5":false,"T6":false,"T7":false,"T8":false},"passed":0,"total":8,"values":{"close":64000.0,"ma50":82262.0,"ma150":83455.33,"ma200":105006.0,"ma200_slope1m":-8757.5,"pct_above_lo52":12.08,"pct_from_hi52":-81.31,"rs":19.2},"rs":19.2},"vcp":{"valid":false,"status":"NONE","pivot":78800.0,"pivot_date":"2026-07-15","depths":[16.6,21.6,21.0,12.4,26.1,25.6],"footprint":"17%-22%-21%-12%-26%-26% 6T","base_days":15,"vdu":0.65,"vol_ratio":0.78,"dist_to_pivot_pct":-18.78,"notes":["✓ 수축 횟수 6회","✓ 베이스 깊이 17%","✗ 수축 축소 위반 2회","✗ 최종 수축 25.6%","✗ 베이스 15일","✓ 드라이업 0.65 (기준 ≤0.85)"],"contractions":[["2026-07-01",98300.0,"2026-07-01",82000.0],["2026-07-02",93900.0,"2026-07-06",73600.0],["2026-07-07",91900.0,"2026-07-07",72600.0],["2026-07-09",92600.0,"2026-07-09",81100.0],["2026-07-10",92500.0,"2026-07-14",68400.0],["2026-07-15",78800.0,"2026-07-22",58600.0]]}},{"ticker":"218410","name":"RFHIC","close":48200.0,"change_pct":7.2303,"stage":{"stage":3,"label":"3단계 · 천장 형성","desc":"분산 신호 — 신규 매수 금지, 보유분 관리","confidence":0.86},"template":{"conds":{"T1":false,"T2":true,"T3":true,"T4":true,"T5":false,"T6":true,"T7":false,"T8":true},"passed":5,"total":8,"values":{"close":48200.0,"ma50":73504.0,"ma150":66516.0,"ma200":57382.5,"ma200_slope1m":2654.25,"pct_above_lo52":109.57,"pct_from_hi52":-62.02,"rs":78.3},"rs":78.3},"vcp":{"valid":false,"status":"NONE","pivot":50000.0,"pivot_date":"2026-07-16","depths":[20.0,18.7,17.7,23.3,12.7,19.0],"footprint":"20%-19%-18%-23%-13%-19% 6T","base_days":16,"vdu":0.53,"vol_ratio":0.73,"dist_to_pivot_pct":-3.6,"notes":["✓ 수축 횟수 6회","✓ 베이스 깊이 20%","✗ 수축 축소 위반 2회","✗ 최종 수축 19.0%","✗ 베이스 16일","✓ 드라이업 0.53 (기준 ≤0.85)"],"contractions":[["2026-06-30",65900.0,"2026-07-03",52700.0],["2026-07-06",60500.0,"2026-07-08",49200.0],["2026-07-08",54700.0,"2026-07-09",45000.0],["2026-07-10",54500.0,"2026-07-14",41800.0],["2026-07-15",52000.0,"2026-07-16",45400.0],["2026-07-16",50000.0,"2026-07-21",40500.0]]}},{"ticker":"230240","name":"에치에프알","close":17180.0,"change_pct":5.9186,"stage":{"stage":3,"label":"3단계 · 천장 형성","desc":"분산 신호 — 신규 매수 금지, 보유분 관리","confidence":0.82},"template":{"conds":{"T1":false,"T2":true,"T3":true,"T4":true,"T5":false,"T6":true,"T7":false,"T8":false},"passed":4,"total":8,"values":{"close":17180.0,"ma50":24011.2,"ma150":21831.93,"ma200":20200.95,"ma200_slope1m":83.45,"pct_above_lo52":50.44,"pct_from_hi52":-56.73,"rs":56.3},"rs":56.3},"vcp":{"valid":false,"status":"NONE","pivot":17970.0,"pivot_date":"2026-07-16","depths":[19.3,18.3],"footprint":"19%-18% 2T","base_days":7,"vdu":0.48,"vol_ratio":0.42,"dist_to_pivot_pct":-4.4,"notes":["✓ 수축 횟수 2회","✓ 베이스 깊이 19%","✓ 수축 축소 위반 0회","✗ 최종 수축 18.3%","✗ 베이스 7일","✓ 드라이업 0.48 (기준 ≤0.85)"],"contractions":[["2026-07-13",18890.0,"2026-07-14",15250.0],["2026-07-16",17970.0,"2026-07-21",14690.0]]}},{"ticker":"067310","name":"하나마이크론","close":36150.0,"change_pct":1.831,"stage":{"stage":3,"label":"3단계 · 천장 형성","desc":"분산 신호 — 신규 매수 금지, 보유분 관리","confidence":0.9},"template":{"conds":{"T1":false,"T2":true,"T3":true,"T4":true,"T5":false,"T6":true,"T7":false,"T8":true},"passed":5,"total":8,"values":{"close":36150.0,"ma50":44488.0,"ma150":36198.0,"ma200":33524.25,"ma200_slope1m":2613.55,"pct_above_lo52":247.6,"pct_from_hi52":-38.21,"rs":90.3},"rs":90.3},"vcp":{"valid":false,"status":"NONE","pivot":41200.0,"pivot_date":"2026-07-20","depths":[17.2,17.5,15.4],"footprint":"17%-17%-15% 3T","base_days":7,"vdu":0.8,"vol_ratio":0.53,"dist_to_pivot_pct":-12.26,"notes":["✓ 수축 횟수 3회","✓ 베이스 깊이 17%","✓ 수축 축소 위반 0회","✗ 최종 수축 15.4%","✗ 베이스 7일","✓ 드라이업 0.80 (기준 ≤0.85)"],"contractions":[["2026-07-13",42850.0,"2026-07-14",35500.0],["2026-07-15",40950.0,"2026-07-16",33800.0],["2026-07-20",41200.0,"2026-07-21",34850.0]]}},{"ticker":"095340","name":"ISC","close":147200.0,"change_pct":4.7687,"stage":{"stage":3,"label":"3단계 · 천장 형성","desc":"분산 신호 — 신규 매수 금지, 보유분 관리","confidence":0.88},"template":{"conds":{"T1":false,"T2":true,"T3":true,"T4":true,"T5":false,"T6":true,"T7":false,"T8":true},"passed":5,"total":8,"values":{"close":147200.0,"ma50":187566.0,"ma150":181046.0,"ma200":157411.0,"ma200_slope1m":9645.0,"pct_above_lo52":167.15,"pct_from_hi52":-49.68,"rs":88.4},"rs":88.4},"vcp":{"valid":false,"status":"NONE","pivot":160000.0,"pivot_date":"2026-07-15","depths":[15.0,16.7,22.5,18.7,15.6,17.7],"footprint":"15%-17%-22%-19%-16%-18% 6T","base_days":21,"vdu":0.51,"vol_ratio":0.31,"dist_to_pivot_pct":-8.0,"notes":["✓ 수축 횟수 6회","✓ 베이스 깊이 15%","✓ 수축 축소 위반 1회","✗ 최종 수축 17.7%","✓ 베이스 21일","✓ 드라이업 0.51 (기준 ≤0.85)"],"contractions":[["2026-06-23",213000.0,"2026-06-24",181000.0],["2026-06-24",204000.0,"2026-07-01",170000.0],["2026-07-01",190600.0,"2026-07-02",147800.0],["2026-07-03",167000.0,"2026-07-08",135700.0],["2026-07-13",169400.0,"2026-07-14",143000.0],["2026-07-15",160000.0,"2026-07-21",131700.0]]}},{"ticker":"145020","name":"휴젤","close":241500.0,"change_pct":9.0293,"stage":{"stage":1,"label":"1단계 · 기반 다지기","desc":"하락 후 바닥 다지기 국면","confidence":0.7},"template":{"conds":{"T1":false,"T2":true,"T3":false,"T4":false,"T5":false,"T6":false,"T7":false,"T8":false},"passed":1,"total":8,"values":{"close":241500.0,"ma50":251100.0,"ma150":251633.33,"ma200":251057.5,"ma200_slope1m":-7802.5,"pct_above_lo52":15.83,"pct_from_hi52":-34.55,"rs":58.1},"rs":58.1},"vcp":{"valid":false,"status":"NONE","pivot":243000.0,"pivot_date":"2026-07-16","depths":[10.0,18.0,13.9,8.8],"footprint":"10%-18%-14%-9% 4T","base_days":15,"vdu":0.62,"vol_ratio":1.12,"dist_to_pivot_pct":-0.62,"notes":["✓ 수축 횟수 4회","✓ 베이스 깊이 10%","✓ 수축 축소 위반 1회","✓ 최종 수축 8.8%","✗ 베이스 15일","✓ 드라이업 0.62 (기준 ≤0.85)"],"contractions":[["2026-07-01",290500.0,"2026-07-01",261500.0],["2026-07-02",286000.0,"2026-07-08",234500.0],["2026-07-13",259500.0,"2026-07-14",223500.0],["2026-07-16",243000.0,"2026-07-22",221500.0]]}},{"ticker":"194700","name":"노바렉스","close":13040.0,"change_pct":2.0344,"stage":{"stage":4,"label":"4단계 · 하락 추세","desc":"매도/관망 국면 — 신규 매수 금지","confidence":1.0},"template":{"conds":{"T1":false,"T2":false,"T3":false,"T4":false,"T5":false,"T6":false,"T7":false,"T8":false},"passed":0,"total":8,"values":{"close":13040.0,"ma50":14247.8,"ma150":14149.27,"ma200":14806.5,"ma200_slope1m":-718.25,"pct_above_lo52":18.65,"pct_from_hi52":-41.0,"rs":49.7},"rs":49.7},"vcp":{"valid":false,"status":"NONE","pivot":15010.0,"pivot_date":"2026-07-13","depths":[15.3],"footprint":"15% 1T","base_days":7,"vdu":0.45,"vol_ratio":0.61,"dist_to_pivot_pct":-13.12,"notes":["✗ 수축 횟수 1회","✓ 베이스 깊이 15%","✓ 수축 축소 위반 0회","✗ 최종 수축 15.3%","✗ 베이스 7일","✓ 드라이업 0.45 (기준 ≤0.85)"],"contractions":[["2026-07-13",15010.0,"2026-07-23",12710.0]]}},{"ticker":"195940","name":"HK이노엔","close":38800.0,"change_pct":4.0214,"stage":{"stage":4,"label":"4단계 · 하락 추세","desc":"매도/관망 국면 — 신규 매수 금지","confidence":1.0},"template":{"conds":{"T1":false,"T2":false,"T3":false,"T4":false,"T5":false,"T6":false,"T7":false,"T8":false},"passed":0,"total":8,"values":{"close":38800.0,"ma50":42092.0,"ma150":48371.67,"ma200":48539.5,"ma200_slope1m":-781.25,"pct_above_lo52":6.01,"pct_from_hi52":-33.79,"rs":47.7},"rs":47.7},"vcp":{"valid":false,"status":"NONE","pivot":42150.0,"pivot_date":"2026-07-13","depths":[9.1,13.2],"footprint":"9%-13% 2T","base_days":17,"vdu":0.49,"vol_ratio":0.61,"dist_to_pivot_pct":-7.95,"notes":["✓ 수축 횟수 2회","✓ 베이스 깊이 9%","✓ 수축 축소 위반 1회","✗ 최종 수축 13.2%","✗ 베이스 17일","✓ 드라이업 0.49 (기준 ≤0.85)"],"contractions":[["2026-06-29",42850.0,"2026-07-13",38950.0],["2026-07-13",42150.0,"2026-07-21",36600.0]]}},{"ticker":"237690","name":"에스티팜","close":117900.0,"change_pct":4.3363,"stage":{"stage":3,"label":"3단계 · 천장 형성","desc":"분산 신호 — 신규 매수 금지, 보유분 관리","confidence":0.67},"template":{"conds":{"T1":false,"T2":true,"T3":true,"T4":false,"T5":false,"T6":true,"T7":false,"T8":true},"passed":4,"total":8,"values":{"close":117900.0,"ma50":126030.0,"ma150":137303.33,"ma200":128118.5,"ma200_slope1m":3053.0,"pct_above_lo52":43.96,"pct_from_hi52":-31.49,"rs":73.8},"rs":73.8},"vcp":{"valid":false,"status":"NONE","pivot":121400.0,"pivot_date":"2026-07-21","depths":[12.0,16.5,14.6,18.6,9.2],"footprint":"12%-16%-15%-19%-9% 5T","base_days":25,"vdu":0.81,"vol_ratio":0.6,"dist_to_pivot_pct":-2.88,"notes":["✓ 수축 횟수 5회","✓ 베이스 깊이 12%","✗ 수축 축소 위반 2회","✓ 최종 수축 9.2%","✓ 베이스 25일","✓ 드라이업 0.81 (기준 ≤0.85)"],"contractions":[["2026-06-17",138600.0,"2026-06-17",122000.0],["2026-06-18",136500.0,"2026-06-22",114000.0],["2026-06-29",137100.0,"2026-07-10",117100.0],["2026-07-13",135400.0,"2026-07-21",110200.0],["2026-07-21",121400.0,"2026-07-21",110200.0]]}},{"ticker":"031330","name":"에스에이엠티","close":10940.0,"change_pct":4.1905,"stage":{"stage":2,"label":"2단계 · 상승 추세","desc":"기관 매집이 유효한 매수 가능 국면 · 50일선 하회 — 2단계 내 눌림/약화 주의","confidence":0.8},"template":{"conds":{"T1":true,"T2":true,"T3":true,"T4":true,"T5":false,"T6":true,"T7":false,"T8":true},"passed":6,"total":8,"values":{"close":10940.0,"ma50":13558.2,"ma150":7940.53,"ma200":6865.65,"ma200_slope1m":862.4,"pct_above_lo52":282.52,"pct_from_hi52":-45.16,"rs":95.5},"rs":95.5},"vcp":{"valid":false,"status":"NONE","pivot":11260.0,"pivot_date":"2026-07-15","depths":[18.6,11.1],"footprint":"19%-11% 2T","base_days":8,"vdu":0.27,"vol_ratio":0.29,"dist_to_pivot_pct":-2.84,"notes":["✓ 수축 횟수 2회","✓ 베이스 깊이 19%","✓ 수축 축소 위반 0회","✓ 최종 수축 11.1%","✗ 베이스 8일","✓ 드라이업 0.27 (기준 ≤0.85)"],"contractions":[["2026-07-10",12100.0,"2026-07-14",9850.0],["2026-07-15",11260.0,"2026-07-20",10010.0]]}},{"ticker":"475830","name":"오름테라퓨틱","close":47700.0,"change_pct":12.3675,"stage":{"stage":1,"label":"1단계 · 기반 다지기","desc":"하락 후 바닥 다지기 국면","confidence":0.56},"template":{"conds":{"T1":false,"T2":true,"T3":true,"T4":false,"T5":false,"T6":true,"T7":false,"T8":true},"passed":4,"total":8,"values":{"close":47700.0,"ma50":59907.0,"ma150":90952.33,"ma200":80398.25,"ma200_slope1m":1992.25,"pct_above_lo52":135.56,"pct_from_hi52":-67.46,"rs":73.2},"rs":73.2},"vcp":{"valid":false,"status":"NONE","pivot":49150.0,"pivot_date":"2026-07-15","depths":[11.4,20.9,17.3,14.9,20.1],"footprint":"11%-21%-17%-15%-20% 5T","base_days":16,"vdu":0.37,"vol_ratio":0.51,"dist_to_pivot_pct":-2.95,"notes":["✓ 수축 횟수 5회","✓ 베이스 깊이 11%","✗ 수축 축소 위반 2회","✗ 최종 수축 20.1%","✗ 베이스 16일","✓ 드라이업 0.37 (기준 ≤0.85)"],"contractions":[["2026-06-30",63400.0,"2026-06-30",56200.0],["2026-07-01",61900.0,"2026-07-03",48950.0],["2026-07-03",54100.0,"2026-07-10",44750.0],["2026-07-10",50500.0,"2026-07-14",43000.0],["2026-07-15",49150.0,"2026-07-21",39250.0]]}},{"ticker":"131290","name":"티에스이","close":239500.0,"change_pct":-0.2083,"stage":{"stage":2,"label":"2단계 · 상승 추세","desc":"기관 매집이 유효한 매수 가능 국면","confidence":1.0},"template":{"conds":{"T1":true,"T2":true,"T3":true,"T4":true,"T5":true,"T6":true,"T7":true,"T8":true},"passed":8,"total":8,"values":{"close":239500.0,"ma50":232880.0,"ma150":144150.67,"ma200":121457.5,"ma200_slope1m":21714.0,"pct_above_lo52":562.52,"pct_from_hi52":-18.54,"rs":97.8},"rs":97.8},"vcp":{"valid":false,"status":"NONE","pivot":287000.0,"pivot_date":"2026-07-20","depths":[20.3,17.3,14.7,16.7],"footprint":"20%-17%-15%-17% 4T","base_days":8,"vdu":0.87,"vol_ratio":0.99,"dist_to_pivot_pct":-16.55,"notes":["✓ 수축 횟수 4회","✓ 베이스 깊이 20%","✓ 수축 축소 위반 0회","✗ 최종 수축 16.7%","✗ 베이스 8일","△ 드라이업 0.87 (기준 ≤0.85)"],"contractions":[["2026-07-10",291000.0,"2026-07-10",232000.0],["2026-07-13",294000.0,"2026-07-14",243000.0],["2026-07-16",292000.0,"2026-07-20",249000.0],["2026-07-20",287000.0,"2026-07-22",239000.0]]}}]